setup.py
sitevcs/__init__.py
sitevcs/info.py
sitevcs.egg-info/PKG-INFO
sitevcs.egg-info/SOURCES.txt
sitevcs.egg-info/dependency_links.txt
sitevcs.egg-info/top_level.txt
sitevcs.egg-info/zip-safe