Metadata-Version: 1.0
Name: sitevcs
Version: 0.1.3
Summary: sitevcs v. 0.1.2
